pymonntorch/__init__.py
pymonntorch/cli.py
pymonntorch/pymonntorch.py
pymonntorch/utils.py
pymonntorch/NetworkBehavior/__init__.py
pymonntorch/NetworkBehavior/Basics/BasicHomeostasis.py
pymonntorch/NetworkBehavior/Basics/Normalization.py
pymonntorch/NetworkBehavior/Basics/__init__.py
pymonntorch/NetworkBehavior/EulerEquationModules/Equation.py
pymonntorch/NetworkBehavior/EulerEquationModules/EulerClock.py
pymonntorch/NetworkBehavior/EulerEquationModules/Helper.py
pymonntorch/NetworkBehavior/EulerEquationModules/VariableInitializer.py
pymonntorch/NetworkBehavior/EulerEquationModules/__init__.py
pymonntorch/NetworkBehavior/Recorder/Recorder.py
pymonntorch/NetworkBehavior/Recorder/__init__.py
pymonntorch/NetworkBehavior/Structure/Structure.py
pymonntorch/NetworkBehavior/Structure/__init__.py
pymonntorch/NetworkCore/AnalysisModule.py
pymonntorch/NetworkCore/Base.py
pymonntorch/NetworkCore/Behavior.py
pymonntorch/NetworkCore/Network.py
pymonntorch/NetworkCore/NeuronGroup.py
pymonntorch/NetworkCore/SynapseGroup.py
pymonntorch/NetworkCore/TaggableObject.py
pymonntorch/NetworkCore/__init__.py
pymonntorch-0.1.4.dist-info/AUTHORS.rst
pymonntorch-0.1.4.dist-info/LICENSE
pymonntorch-0.1.4.dist-info/METADATA
pymonntorch-0.1.4.dist-info/WHEEL
pymonntorch-0.1.4.dist-info/entry_points.txt
pymonntorch-0.1.4.dist-info/top_level.txt
pymonntorch-0.1.4.dist-info/RECORD
