Metadata-Version: 2.1
Name: pymonntorch
Version: 0.1.4
Summary: PymoNNtorch is a Pytorch version of PymoNNto
Home-page: https://github.com/cnrl/PymoNNtorch
Author: Computational Neuroscience Research Laboratory
Author-email: ashenatena@gmail.com
License: MIT license
Keywords: pymonntorch
Classifier: Development Status :: 2 - Pre-Alpha
Classifier: Intended Audience :: Developers
Classifier: License :: OSI Approved :: MIT License
Classifier: Natural Language :: English
Classifier: Programming Language :: Python :: 3
Classifier: Programming Language :: Python :: 3.8
Classifier: Programming Language :: Python :: 3.9
Classifier: Programming Language :: Python :: 3.10
Requires-Python: >=3.8
License-File: LICENSE
License-File: AUTHORS.rst
Requires-Dist: numpy >=1.21.0
Requires-Dist: torch >=1.11.0
